fingerprint.py
monad_utils_kit-0.1.0.dist-info/licenses/LICENSE
monad_utils_kit-0.1.0.dist-info/METADATA
monad_utils_kit-0.1.0.dist-info/WHEEL
monad_utils_kit-0.1.0.dist-info/entry_points.txt
monad_utils_kit-0.1.0.dist-info/top_level.txt
monad_utils_kit-0.1.0.dist-info/RECORD
