Metadata-Version: 2.4
Name: monad-utils-kit
Version: 0.1.0
Summary: CLI tools for interacting with Monad testnet
Author: Naufel Aniq
Author-email: Naufel Aniq <aniqraaj786@gmail.com>
License: MIT
Requires-Python: >=3.7
License-File: LICENSE
Dynamic: author
Dynamic: license-file
Dynamic: requires-python
